artmr/__init__.py
artmr/artmr.py
artmr/models.py
artmr/views.py
artmr-1.0.dist-info/METADATA
artmr-1.0.dist-info/RECORD
artmr-1.0.dist-info/WHEEL
artmr-1.0.dist-info/entry_points.txt
artmr-1.0.dist-info/top_level.txt
