Metadata-Version: 2.1
Name: artmr
Version: 1.0
Summary: Offline race timing console application
Home-page: https://github.com/mronkain/artmr
Author: mronkain
Author-email: mrnk@iki.fi
License: UNKNOWN
Platform: UNKNOWN
Classifier: Programming Language :: Python :: 2.7
Classifier: Programming Language :: Python :: 3
Classifier: Programming Language :: Python :: 3.5
Classifier: Programming Language :: Python :: 3.6
Classifier: License :: OSI Approved :: MIT License
Classifier: Operating System :: POSIX
Classifier: Environment :: Console
Classifier: Intended Audience :: End Users/Desktop
Classifier: Topic :: Utilities
Requires-Python: >=2.6, !=3.0.*, !=3.1.*, !=3.2.*, <4
Requires-Dist: asciimatics (>=1.9)
Requires-Dist: sqlobject
Requires-Dist: pandas
